sleeptimer/__init__.py
sleeptimer-1.0.1.dist-info/LICENSE
sleeptimer-1.0.1.dist-info/METADATA
sleeptimer-1.0.1.dist-info/WHEEL
sleeptimer-1.0.1.dist-info/top_level.txt
sleeptimer-1.0.1.dist-info/RECORD
